interloper.py
interloper-0.1.4.dist-info/licenses/LICENSE
interloper-0.1.4.dist-info/METADATA
interloper-0.1.4.dist-info/WHEEL
interloper-0.1.4.dist-info/top_level.txt
interloper-0.1.4.dist-info/RECORD
