Metadata-Version: 2.4
Name: interloper
Version: 0.1.4
Summary: Tool to run ecs execute command in lambda.
Home-page: https://github.com/theherk/interloper
Author: Adam Sherwood
Author-email: theherk@gmail.com
Project-URL: Bug Tracker, https://github.com/theherk/interloper/issues
Classifier: Programming Language :: Python :: 3
Classifier: License :: OSI Approved :: MIT License
Classifier: Operating System :: OS Independent
Requires-Python: >=3.7
License-File: LICENSE
Requires-Dist: boto3
Requires-Dist: websocket-client
Dynamic: license-file
